{"cameraMode":{"drawMode":0,"name":"Shaded","section":"Shading Mode"},"sceneLighting":true,"audioPlay":false,"sceneViewState":{"showFog":true,"showMaterialUpdate":false,"showSkybox":true,"showFlares":true,"showImageEffects":true,"showParticleSystems":true},"in2DMode":false,"pivot":{"x":5.939613342285156,"y":-2.3279027938842775,"z":7.881111145019531},"rotation":{"x":-0.1977698653936386,"y":-0.144388809800148,"z":0.029465869069099428,"w":-0.9691121578216553},"size":18.24229621887207,"orthographic":false}